README.rst
setup.py
contentful/__init__.py
contentful.py.egg-info/PKG-INFO
contentful.py.egg-info/SOURCES.txt
contentful.py.egg-info/dependency_links.txt
contentful.py.egg-info/requires.txt
contentful.py.egg-info/top_level.txt
contentful/cda/__init__.py
contentful/cda/client.py
contentful/cda/const.py
contentful/cda/errors.py
contentful/cda/fields.py
contentful/cda/resources.py
contentful/cda/serialization.py
contentful/cda/utils.py
contentful/cda/version.py
test/test_client.py
test/test_resources.py
test/test_serialization.py
test/test_utils.py