Metadata-Version: 1.1
Name: contentful.py
Version: 0.9.3
Summary: Python SDK for Contentful's Content Delivery API
Home-page: https://github.com/contentful-labs/contentful.py
Author: Contentful GmbH
Author-email: python@contentful.com
License: Apache 2.0
Platform: UNKNOWN
Classifier: Development Status :: 3 - Alpha
Classifier: Intended Audience :: Developers
Classifier: License :: OSI Approved :: Apache Software License
Classifier: Programming Language :: Python :: 2.7
Classifier: Programming Language :: Python :: 3
Classifier: Programming Language :: Python :: 3.2
Classifier: Programming Language :: Python :: 3.3
Classifier: Programming Language :: Python :: 3.4
Classifier: Programming Language :: Python :: 3.5
